Metadata-Version: 1.0
Name: Vins-server-messenger
Version: 0.2
Summary: Vins__server_messenger
Home-page: UNKNOWN
Author: Gregory Vins
Author-email: gregoryvins@gmail.com
License: UNKNOWN
Platform: UNKNOWN
